dbg/__init__.py
dbg/core.py
dbg/logger.py
dbg/types.py
dbg/data/__init__.py
dbg/data/grammar.py
dbg/data/input.py
dbg/data/oracle.py
dbg/data/tree.py
dbg/explanation/__init__.py
dbg/explanation/candidate.py
dbg/generator/__init__.py
dbg/generator/engine.py
dbg/generator/generator.py
dbg/learner/__init__.py
dbg/learner/learner.py
dbg/learner/metric.py
dbg/learner/negation.py
dbg/learner/pattern_learner.py
dbg/runner/__init__.py
dbg/runner/runner.py
dbg_framework-0.0.2.dist-info/LICENSE
dbg_framework-0.0.2.dist-info/METADATA
dbg_framework-0.0.2.dist-info/WHEEL
dbg_framework-0.0.2.dist-info/top_level.txt
dbg_framework-0.0.2.dist-info/RECORD
