Metadata-Version: 2.2
Name: dbg-framework
Version: 0.0.2
Author-email: Martin Eberlein <martin.eberlein@hu-berlin.de>
Classifier: Intended Audience :: Science/Research
Classifier: License :: OSI Approved :: MIT License
Classifier: Programming Language :: Python :: 3.11
Classifier: Operating System :: OS Independent
Classifier: Topic :: Scientific/Engineering
Classifier: Topic :: Software Development :: Testing
Requires-Python: >=3.10
License-File: LICENSE
Requires-Dist: pandas
Provides-Extra: test
Requires-Dist: pytest>=7.2.2; extra == "test"
Requires-Dist: pytest-cov>=4.1.0; extra == "test"
Requires-Dist: pytest-html>=3.2.0; extra == "test"
Requires-Dist: pytest-rerunfailures>=11.1.2; extra == "test"
Requires-Dist: parameterized>=0.8.1; extra == "test"
